[
    {
      "title": "Electrician",
      "location": "Mumbai",
      "salary": "1000 rs",
      "date": "25/03/2025",
      "applyLink": "https://apply.example.com/electrician"
    },
    {
      "title": "Plumber",
      "location": "Delhi",
      "salary": "1200 rs",
      "date": "28/03/2025",
      "applyLink": "https://apply.example.com/plumber"
    },
    {
      "title": "Carpenter",
      "location": "Bangalore",
      "salary": "1500 rs",
      "date": "30/03/2025",
      "applyLink": "https://apply.example.com/carpenter"
    }
  ]
  